[
  {"question": "ما هو عاصمة الجزائر؟", "answer": "الجزائر"},
  {"question": "كم يساوي 5 + 7؟", "answer": "12"},
  {"question": "من هو مخترع الهاتف؟", "answer": "غراهام بيل"},
  {"question": "ما هي أكبر قارة في العالم؟", "answer": "آسيا"},
  {"question": "ما هو الكوكب الأحمر؟", "answer": "المريخ"},
  {"question": "كم عدد قارات العالم؟", "answer": "7"},
  {"question": "من هو مؤسس مايكروسوفت؟", "answer": "بيل غيتس"},
  {"question": "ما هي لغة برمجة بايثون؟", "answer": "لغة برمجة"},
  {"question": "ما هو أكبر محيط في العالم؟", "answer": "المحيط الهادئ"},
  {"question": "كم عدد أحرف اللغة العربية؟", "answer": "28"},
  {"question": "ما هو الحيوان الذي يلقب بملك الغابة؟", "answer": "الأسد"},
  {"question": "في أي قارة تقع مصر؟", "answer": "أفريقيا"},
  {"question": "كم عدد أيام السنة الكبيسة؟", "answer": "366"},
  {"question": "ما هي عاصمة فرنسا؟", "answer": "باريس"},
  {"question": "ما اسم أول إنسان صعد إلى القمر؟", "answer": "نيل أرمسترونغ"},
  {"question": "كم عدد الكواكب في المجموعة الشمسية؟", "answer": "8"},
  {"question": "ما هي أسرع حيوان بري؟", "answer": "الفهد"},
  {"question": "من هو النبي الذي ابتلعه الحوت؟", "answer": "يونس"},
  {"question": "كم عدد أركان الإسلام؟", "answer": "5"},
  {"question": "ما هو لون دم الإنسان؟", "answer": "أحمر"},
  {"question": "كم عدد اللاعبين في فريق كرة القدم؟", "answer": "11"},
  {"question": "ما هي عاصمة المغرب؟", "answer": "الرباط"},
  {"question": "من هو أول خليفة للمسلمين؟", "answer": "أبو بكر"},
  {"question": "ما هي وحدة قياس الكهرباء؟", "answer": "الفولت"},
  {"question": "أطول نهر في العالم هو؟", "answer": "النيل"},
  {"question": "ما هو الحيوان الذي يبيض ولا يلد؟", "answer": "الدجاجة"},
  {"question": "أين تقع مكة المكرمة؟", "answer": "السعودية"},
  {"question": "ما اسم أسرع طائر؟", "answer": "النعامة"},
  {"question": "كم عدد قلوب الأخطبوط؟", "answer": "3"},
  {"question": "ما هو أصغر كوكب في المجموعة الشمسية؟", "answer": "عطارد"},
  {"question": "ما اسم عاصمة تركيا؟", "answer": "أنقرة"},
  {"question": "من هو مؤسس شركة آبل؟", "answer": "ستيف جوبز"},
  {"question": "ما هو الغاز الذي نتنفسه؟", "answer": "الأكسجين"},
  {"question": "كم عدد ألوان قوس قزح؟", "answer": "7"},
  {"question": "ما هي عاصمة العراق؟", "answer": "بغداد"},
  {"question": "أين تقع مدينة دبي؟", "answer": "الإمارات"},
  {"question": "كم عدد العظام في جسم الإنسان؟", "answer": "206"},
  {"question": "من هو مخترع المصباح الكهربائي؟", "answer": "توماس إديسون"},
  {"question": "ما هي عاصمة اليابان؟", "answer": "طوكيو"},
  {"question": "ما اسم أكبر صحراء في العالم؟", "answer": "الصحراء الكبرى"},
  {"question": "من هو النبي الذي فُدي بذبح عظيم؟", "answer": "إسماعيل"},
  {"question": "ما هي لغة القرآن الكريم؟", "answer": "العربية"},
  {"question": "كم عدد ساعات اليوم؟", "answer": "24"},
  {"question": "من هو أسرع لاعب كرة القدم في العالم؟", "answer": "مبابي"},
  {"question": "ما هو الحيوان الذي يعيش في القطب الجنوبي؟", "answer": "البطريق"},
  {"question": "ما اسم الدولة التي عاصمتها مدريد؟", "answer": "إسبانيا"},
  {"question": "من هو أول نبي؟", "answer": "آدم"},
  {"question": "ما اسم عاصمة لبنان؟", "answer": "بيروت"},
  {"question": "ما هي أصغر دولة في العالم؟", "answer": "الفاتيكان"}
]
